deltalanguage/DeltaStyle.xml
deltalanguage/__about__.py
deltalanguage/__init__.py
deltalanguage/_utils.py
deltalanguage/logging.py
deltalanguage/data_types/__init__.py
deltalanguage/data_types/_delta_types.py
deltalanguage/data_types/_exceptions.py
deltalanguage/data_types/_special.py
deltalanguage/data_types/dotdf.capnp
deltalanguage/lib/__init__.py
deltalanguage/lib/primitives.py
deltalanguage/runtime/__init__.py
deltalanguage/runtime/_output.py
deltalanguage/runtime/_queues.py
deltalanguage/runtime/_runtime.py
deltalanguage/test/__init__.py
deltalanguage/test/_graph_lib.py
deltalanguage/test/_node_lib.py
deltalanguage/test/_utils.py
deltalanguage/test/test_body_selection.py
deltalanguage/test/test_const_folding.py
deltalanguage/test/test_decorators.py
deltalanguage/test/test_delta_graph.py
deltalanguage/test/test_doctest.py
deltalanguage/test/test_graph_deserialisation.py
deltalanguage/test/test_graph_serialisation.py
deltalanguage/test/test_graph_splitting.py
deltalanguage/test/test_interactive_node.py
deltalanguage/test/test_migen_template.py
deltalanguage/test/test_multiple_output_blocks.py
deltalanguage/test/test_no_body_node.py
deltalanguage/test/test_node_bodies.py
deltalanguage/test/test_node_key.py
deltalanguage/test/test_node_serialisation.py
deltalanguage/test/test_node_templates.py
deltalanguage/test/test_outport_naming.py
deltalanguage/test/test_ports.py
deltalanguage/test/test_protocol_adaptor.py
deltalanguage/test/test_real_node.py
deltalanguage/test/test_single_output_indexing.py
deltalanguage/test/test_types.py
deltalanguage/test/test_utils.py
deltalanguage/test/test_visualisation.py
deltalanguage/test/test_wiring.py
deltalanguage/test/data/graph_capnp.json
deltalanguage/test/data/graph_multibody_capnp.json
deltalanguage/test/data/graph_str.txt
deltalanguage/test/data/graph_with_migen_capnp.json
deltalanguage/test/examples/__init__.py
deltalanguage/test/examples/test_examples.py
deltalanguage/test/execution/__init__.py
deltalanguage-0.6.4.dist-info/LICENSE.rst
deltalanguage-0.6.4.dist-info/METADATA
deltalanguage-0.6.4.dist-info/WHEEL
deltalanguage-0.6.4.dist-info/top_level.txt
deltalanguage-0.6.4.dist-info/RECORD
