Metadata-Version: 2.1
Name: deltalanguage
Version: 0.6.4
Summary: Hosted programming language for Deltaflow
Home-page: https://github.com/riverlane/deltalanguage
Author: Riverlane
Author-email: deltaflow@riverlane.com
License: MIT License with Commons Clause
Platform: Ubuntu 20.04
Classifier: Development Status :: 5 - Production/Stable
Classifier: Environment :: Console
Classifier: Intended Audience :: Developers
Classifier: Intended Audience :: Science/Research
Classifier: License :: Free for non-commercial use
Classifier: Operating System :: POSIX :: Linux
Classifier: Programming Language :: Python :: 3
Requires-Python: ==3.8.*
Requires-Dist: attrs (>=20.2)
Requires-Dist: dill (>=0.3)
Requires-Dist: migen (>=0.9.2)
Requires-Dist: numpy (>=1.20)
Requires-Dist: pycapnp (>=0.6)
Requires-Dist: tqdm (>=4.51)
Provides-Extra: visualisation
Requires-Dist: jupyter (>=1.0) ; extra == 'visualisation'
Requires-Dist: matplotlib (>=3.3) ; extra == 'visualisation'
Requires-Dist: networkx (>=2.5) ; extra == 'visualisation'
Requires-Dist: progress (>=1.5) ; extra == 'visualisation'
